functionwords/__init__.py
functionwords/base.py
functionwords/resources/chinese_classical_comprehensive.json
functionwords/resources/chinese_classical_naive.json
functionwords/resources/chinese_comprehensive.json
functionwords/resources/chinese_simplified_modern.json
functionwords/resources/description.json
functionwords/resources/english.json
functionwords-0.8.dist-info/WHEEL
functionwords-0.8.dist-info/METADATA
functionwords-0.8.dist-info/RECORD
