Metadata-Version: 2.1
Name: functionwords
Version: 0.8
Summary: Extract curated Chinese and English function words from texts.
Home-page: https://github.com/Wang-Haining/functionwords
License: CC-BY-SA 4.0
Author: Haining Wang
Author-email: hw56@indiana.edu
Requires-Python: >=3.8,<4.0
Classifier: License :: Other/Proprietary License
Classifier: Programming Language :: Python :: 3
Classifier: Programming Language :: Python :: 3.10
Classifier: Programming Language :: Python :: 3.8
Classifier: Programming Language :: Python :: 3.9
Project-URL: Repository, https://github.com/Wang-Haining/functionwords
